test/__init__.py
test/dfa_test.py
test/turing_test.py
theory_of_computation/__init__.py
theory_of_computation/dfa.py
theory_of_computation/turing_machine_divisible_by_3.py
theory_of_computation/utils.py
theory_of_computation-1.0.1.dist-info/licenses/LICENSE
theory_of_computation-1.0.1.dist-info/METADATA
theory_of_computation-1.0.1.dist-info/WHEEL
theory_of_computation-1.0.1.dist-info/top_level.txt
theory_of_computation-1.0.1.dist-info/RECORD
